<laserDevice>
  <originBottomLeft>false</originBottomLeft>
  <jobSentText>Job was sent as &apos;$jobname&apos;
Please:
-Close the lid
-Turn on ventilation
-And press &apos;start&apos;</jobSentText>
  <jobPrefix>visicut </jobPrefix>
  <laserCutter class="com.t_oster.liblasercut.drivers.ThunderLaser">
    <BedWidth>900.0</BedWidth>
    <BedHeight>600.0</BedHeight>
    <LaserPowerMax>70</LaserPowerMax>
    <MaxVectorCutSpeed>1000</MaxVectorCutSpeed>
    <MaxVectorMoveSpeed>1000</MaxVectorMoveSpeed>
    <hostname>127.0.0.1</hostname>
  </laserCutter>
  <cameraTiming>0</cameraTiming>
  <projectorTiming>0</projectorTiming>
  <projectorWidth>0</projectorWidth>
  <projectorHeight>0</projectorHeight>
  <description>ThunderLaser 644xg</description>
  <thumbnailPath>ThunderLaser_Nova35_FabLabNbg.png</thumbnailPath>
  <name>ThunderLaser</name>
</laserDevice>
